pyramid_braintree
