Metadata-Version: 1.1
Name: pyramid-braintree
Version: 0.1.1
Summary: Braintree initializer for the Pyramid Web Framework
Home-page: https://github.com/dfee/pyramid_braintree
Author: Devin Fee
Author-email: devin.fee@gmail.com
License: BSD-derived (http://www.repoze.org/LICENSE.txt)
Keywords: braintree pyramid payments
Platform: UNKNOWN
Classifier: Intended Audience :: Developers
Classifier: Programming Language :: Python
Classifier: Programming Language :: Python :: 2.7
Classifier: Programming Language :: Python :: 3
Classifier: Programming Language :: Python :: 3.2
Classifier: Framework :: Pyramid
